{
    "description": "",
    "tags": [],
    "size": {
        "height": 426,
        "width": 320
    },
    "objects": [
        {
            "id": 56636752,
            "classId": 122195,
            "description": "",
            "geometryType": "rectangle",
            "labelerLogin": "cxnt",
            "createdAt": "2021-10-11T14:03:05.521Z",
            "updatedAt": "2021-10-11T14:03:05.521Z",
            "tags": [
                {
                    "id": 958479,
                    "tagId": 236195,
                    "name": "confidence",
                    "value": 0.4448,
                    "labelerLogin": "cxnt",
                    "createdAt": "2021-10-11T14:03:05.521Z",
                    "updatedAt": "2021-10-11T14:03:05.521Z"
                }
            ],
            "classTitle": "person",
            "points": {
                "exterior": [
                    [
                        83,
                        54
                    ],
                    [
                        293,
                        421
                    ]
                ],
                "interior": []
            }
        }
    ]
}