{
    "description": "",
    "tags": [],
    "size": {
        "height": 500,
        "width": 330
    },
    "objects": [
        {
            "id": 56637142,
            "classId": 122195,
            "description": "",
            "geometryType": "rectangle",
            "labelerLogin": "cxnt",
            "createdAt": "2021-10-11T14:03:05.521Z",
            "updatedAt": "2021-10-11T14:03:05.521Z",
            "tags": [
                {
                    "id": 958869,
                    "tagId": 236195,
                    "name": "confidence",
                    "value": 0.7002,
                    "labelerLogin": "cxnt",
                    "createdAt": "2021-10-11T14:03:05.521Z",
                    "updatedAt": "2021-10-11T14:03:05.521Z"
                }
            ],
            "classTitle": "person",
            "points": {
                "exterior": [
                    [
                        204,
                        137
                    ],
                    [
                        243,
                        212
                    ]
                ],
                "interior": []
            }
        }
    ]
}