{
    "description": "",
    "tags": [],
    "size": {
        "height": 375,
        "width": 500
    },
    "objects": [
        {
            "id": 56636956,
            "classId": 122195,
            "description": "",
            "geometryType": "rectangle",
            "labelerLogin": "cxnt",
            "createdAt": "2021-10-11T14:03:05.521Z",
            "updatedAt": "2021-10-11T14:03:05.521Z",
            "tags": [
                {
                    "id": 958683,
                    "tagId": 236195,
                    "name": "confidence",
                    "value": 0.7983,
                    "labelerLogin": "cxnt",
                    "createdAt": "2021-10-11T14:03:05.521Z",
                    "updatedAt": "2021-10-11T14:03:05.521Z"
                }
            ],
            "classTitle": "person",
            "points": {
                "exterior": [
                    [
                        6,
                        93
                    ],
                    [
                        204,
                        342
                    ]
                ],
                "interior": []
            }
        },
        {
            "id": 56636955,
            "classId": 122195,
            "description": "",
            "geometryType": "rectangle",
            "labelerLogin": "cxnt",
            "createdAt": "2021-10-11T14:03:05.521Z",
            "updatedAt": "2021-10-11T14:03:05.521Z",
            "tags": [
                {
                    "id": 958682,
                    "tagId": 236195,
                    "name": "confidence",
                    "value": 0.8315,
                    "labelerLogin": "cxnt",
                    "createdAt": "2021-10-11T14:03:05.521Z",
                    "updatedAt": "2021-10-11T14:03:05.521Z"
                }
            ],
            "classTitle": "person",
            "points": {
                "exterior": [
                    [
                        316,
                        126
                    ],
                    [
                        499,
                        373
                    ]
                ],
                "interior": []
            }
        },
        {
            "id": 56636954,
            "classId": 122195,
            "description": "",
            "geometryType": "rectangle",
            "labelerLogin": "cxnt",
            "createdAt": "2021-10-11T14:03:05.521Z",
            "updatedAt": "2021-10-11T14:03:05.521Z",
            "tags": [
                {
                    "id": 958681,
                    "tagId": 236195,
                    "name": "confidence",
                    "value": 0.8838,
                    "labelerLogin": "cxnt",
                    "createdAt": "2021-10-11T14:03:05.521Z",
                    "updatedAt": "2021-10-11T14:03:05.521Z"
                }
            ],
            "classTitle": "person",
            "points": {
                "exterior": [
                    [
                        217,
                        15
                    ],
                    [
                        339,
                        176
                    ]
                ],
                "interior": []
            }
        }
    ]
}